{"properties": [
  {
    "name": "spring.training.datasource.driver-class-name",
    "type": "java.lang.String",
    "description": "A description for 'spring.training.datasource.driver-class-name'"
  },
  {
    "name": "spring.training.datasource.url",
    "type": "java.lang.String",
    "description": "A description for 'spring.training.datasource.url'"
  },
  {
    "name": "spring.training.datasource.username",
    "type": "java.lang.String",
    "description": "A description for 'spring.training.datasource.username'"
  },
  {
    "name": "spring.training.datasource.password",
    "type": "java.lang.String",
    "description": "A description for 'spring.training.datasource.password'"
  },
  {
    "name": "spring.training.datasource.dbcp.test-while-idle",
    "type": "java.lang.String",
    "description": "A description for 'spring.training.datasource.dbcp.test-while-idle'"
  },
  {
    "name": "spring.training.datasource.dbcp.test-while-idle",
    "type": "java.lang.String",
    "description": "A description for 'spring.training.datasource.dbcp.test-while-idle'"
  },
  {
    "name": "spring.training.datasource.dbcp.validation-query",
    "type": "java.lang.String",
    "description": "A description for 'spring.training.datasource.dbcp.validation-query'"
  },
  {
    "name": "spring.qms.datasource.driver-class-name",
    "type": "java.lang.String",
    "description": "A description for 'spring.qms.datasource.driver-class-name'"
  },
  {
    "name": "spring.qms.datasource.url",
    "type": "java.lang.String",
    "description": "A description for 'spring.qms.datasource.url'"
  },
  {
    "name": "spring.qms.datasource.username",
    "type": "java.lang.String",
    "description": "A description for 'spring.qms.datasource.username'"
  },
  {
    "name": "spring.qms.datasource.password",
    "type": "java.lang.String",
    "description": "A description for 'spring.qms.datasource.password'"
  },
  {
    "name": "spring.qms.dbcp.test-while-idle",
    "type": "java.lang.String",
    "description": "A description for 'spring.qms.dbcp.test-while-idle'"
  },
  {
    "name": "spring.qms.dbcp.validation-query",
    "type": "java.lang.String",
    "description": "A description for 'spring.qms.dbcp.validation-query'"
  },
  {
    "name": "spring.jpa.format-sql",
    "type": "java.lang.String",
    "description": "A description for 'spring.jpa.format-sql'"
  },
  {
    "name": "app.jwt.signingKey",
    "type": "java.lang.String",
    "description": "A description for 'app.jwt.signingKey'"
  },
  {
    "name": "spring.training.datasource.driver-class-name",
    "type": "java.lang.String",
    "description": "A description for 'spring.training.datasource.driver-class-name'"
  },
  {
    "name": "spring.training.datasource.url",
    "type": "java.lang.String",
    "description": "A description for 'spring.training.datasource.url'"
  },
  {
    "name": "spring.training.datasource.username",
    "type": "java.lang.String",
    "description": "A description for 'spring.training.datasource.username'"
  },
  {
    "name": "spring.training.datasource.password",
    "type": "java.lang.String",
    "description": "A description for 'spring.training.datasource.password'"
  },
  {
    "name": "spring.training.datasource.dbcp.test-while-idle",
    "type": "java.lang.String",
    "description": "A description for 'spring.training.datasource.dbcp.test-while-idle'"
  },
  {
    "name": "spring.training.datasource.dbcp.validation-query",
    "type": "java.lang.String",
    "description": "A description for 'spring.training.datasource.dbcp.validation-query'"
  }
]}